agentstable/__init__.py
agentstable/action_generator.py
agentstable/anthropic_tools.py
agentstable/auth.py
agentstable/component_discovery.py
agentstable/components.py
agentstable/execute.py
agentstable/memory.py
agentstable/parallel.py
agentstable/search.py
agentstable/streaming.py
agentstable/tools.py
agentstable/usage.py
agentstable-0.1.4.dist-info/METADATA
agentstable-0.1.4.dist-info/WHEEL
agentstable-0.1.4.dist-info/top_level.txt
agentstable-0.1.4.dist-info/RECORD
